Metadata-Version: 2.2
Name: Betrand-ngoh-mutagha-version-2
Version: 0.2.2
Home-page: https://github.com/Betrand1999/cicd
Author: BETRAND MUTAGHA
Author-email: mutagha2@gmail.com
Classifier: Development Status :: 4 - Beta
Classifier: License :: OSI Approved :: MIT License
Classifier: Programming Language :: Python :: 3
Classifier: Programming Language :: Python :: 3.9
Classifier: Programming Language :: Python :: 3.10
Requires-Dist: flask
Dynamic: author
Dynamic: author-email
Dynamic: classifier
Dynamic: home-page
Dynamic: requires-dist
